inuxnetutil.py
inuxnetutil-0.1.2.dist-info/LICENSE.txt
inuxnetutil-0.1.2.dist-info/METADATA
inuxnetutil-0.1.2.dist-info/WHEEL
inuxnetutil-0.1.2.dist-info/entry_points.txt
inuxnetutil-0.1.2.dist-info/top_level.txt
inuxnetutil-0.1.2.dist-info/RECORD
