Metadata-Version: 2.1
Name: inuxnetutil
Version: 0.1.2
Summary: Set of common handy functions and tools.
Home-page: https://newgit.inuxnet.org/devel/inuxnetutil.git
Author: Jess Williams
Author-email: Jess Williams <devel@inuxnet.org>
License: MIT License
Project-URL: Homepage, https://newgit.inuxnet.org/devel/inuxnetutil.git
Project-URL: Documentation, https://newgit.inuxnet.org/devel/inuxnetutil.git
Project-URL: Repository, https://newgit.inuxnet.org/devel/inuxnetutil.git
Keywords: validation,encrypt,decrypt,inuxnet
Classifier: Intended Audience :: Developers
Classifier: Intended Audience :: System Administrators
Classifier: License :: OSI Approved :: MIT License
Classifier: Programming Language :: Python :: 3
Classifier: Operating System :: OS Independent
Requires-Python: >=3.8
License-File: LICENSE.txt
Requires-Dist: cryptography (>=44.0.0)
